pyroborock_fork/__init__.py
pyroborock_fork-1.1.10.dist-info/METADATA
pyroborock_fork-1.1.10.dist-info/WHEEL
pyroborock_fork-1.1.10.dist-info/top_level.txt
pyroborock_fork-1.1.10.dist-info/RECORD
