Metadata-Version: 2.1
Name: pyroborock_fork
Version: 1.1.10
Summary: Communicate with roborock over tuya protocol
Requires-Dist: pytuyapi-ipc (==1.0.4)
Requires-Dist: python-miio (==0.5.12)
Requires-Dist: pycryptodome (==3.15.0)
